django_googleadsauth-0.1.0.dist-info/licenses/LICENSE
googleadsauth/__init__.py
googleadsauth/admin.py
googleadsauth/apps.py
googleadsauth/models.py
googleadsauth/settings.py
googleadsauth/urls.py
googleadsauth/views.py
googleadsauth/migrations/0001_initial.py
googleadsauth/migrations/__init__.py
tests/__init__.py
tests/conftest.py
tests/test_models.py
tests/test_settings.py
tests/test_views.py
tests/urls.py
django_googleadsauth-0.1.0.dist-info/METADATA
django_googleadsauth-0.1.0.dist-info/WHEEL
django_googleadsauth-0.1.0.dist-info/top_level.txt
django_googleadsauth-0.1.0.dist-info/RECORD
