Metadata-Version: 2.4
Name: django-googleadsauth
Version: 0.1.0
Summary: Django app for Google Ads API authentication and basic functionality
Home-page: https://github.com/tarikwaleed/django-googleadsauth
Author: Tarek Walid
Author-email: tarek@otomatika.tech
Project-URL: Bug Tracker, https://github.com/tarikwaleed/django-googleadsauth/issues
Project-URL: Documentation, https://github.com/tarikwaleed/django-googleadsauth#readme
Project-URL: Source Code, https://github.com/tarikwaleed/django-googleadsauth
Keywords: django,google ads,google api,authentication,oauth2,campaign management
Classifier: Development Status :: 3 - Alpha
Classifier: Environment :: Web Environment
Classifier: Framework :: Django
Classifier: Framework :: Django :: 3.2
Classifier: Framework :: Django :: 4.0
Classifier: Framework :: Django :: 4.1
Classifier: Framework :: Django :: 4.2
Classifier: Intended Audience :: Developers
Classifier: License :: OSI Approved :: MIT License
Classifier: Operating System :: OS Independent
Classifier: Programming Language :: Python
Classifier: Programming Language :: Python :: 3
Classifier: Programming Language :: Python :: 3.7
Classifier: Programming Language :: Python :: 3.8
Classifier: Programming Language :: Python :: 3.9
Classifier: Programming Language :: Python :: 3.10
Classifier: Topic :: Internet :: WWW/HTTP
Classifier: Topic :: Software Development :: Libraries :: Python Modules
Requires-Python: >=3.7
License-File: LICENSE
Requires-Dist: Django>=3.2
Requires-Dist: google-ads>=18.0.0
Requires-Dist: google-auth-oauthlib>=0.4.6
Requires-Dist: google-api-python-client>=2.0.0
Requires-Dist: google-auth>=2.0.0
Requires-Dist: djangorestframework>=3.12.0
Requires-Dist: requests>=2.25.0
Dynamic: author
Dynamic: author-email
Dynamic: classifier
Dynamic: description
Dynamic: description-content-type
Dynamic: home-page
Dynamic: keywords
Dynamic: license-file
Dynamic: project-url
Dynamic: requires-dist
Dynamic: requires-python
Dynamic: summary
